minaki/__init__.py
minaki/cli.py
minaki/plugin_manager.py
minaki/commands/__init__.py
minaki/commands/disable.py
minaki/commands/enable.py
minaki/commands/install.py
minaki/commands/list.py
minaki/commands/list_plugins.py
minaki/commands/logger.py
minaki/commands/remove.py
minaki/commands/run.py
minaki/commands/update.py
minaki_cli-0.1.2.dist-info/METADATA
minaki_cli-0.1.2.dist-info/WHEEL
minaki_cli-0.1.2.dist-info/entry_points.txt
minaki_cli-0.1.2.dist-info/top_level.txt
minaki_cli-0.1.2.dist-info/RECORD
